synthdid/__init__.py
synthdid/get_data.py
synthdid/placebo_simulations.py
synthdid/plots.py
synthdid/sdid.py
synthdid/solver.py
synthdid/summary.py
synthdid/synthdid.py
synthdid/utils.py
synthdid/vcov.py
synthdid-0.10.1.dist-info/LICENSE
synthdid-0.10.1.dist-info/METADATA
synthdid-0.10.1.dist-info/WHEEL
synthdid-0.10.1.dist-info/top_level.txt
synthdid-0.10.1.dist-info/RECORD
