Metadata-Version: 2.1
Name: synthdid
Version: 0.10.1
Summary: Synthdid
Home-page: https://github.com/d2cml-ai/synthdid.py
Author: D2CML Team, Alexander Quispe, Rodrigo  Grijalba, Jhon Flores, Franco Caceres
License: MIT
Keywords: causal-inference
Classifier: Intended Audience :: Developers
Classifier: Intended Audience :: Education
Classifier: Intended Audience :: Science/Research
Classifier: License :: OSI Approved :: Apache Software License
Classifier: Topic :: Scientific/Engineering
License-File: LICENSE
Requires-Dist: appdirs ==1.4.3
Requires-Dist: contourpy ==1.0.7
Requires-Dist: cycler ==0.11.0
Requires-Dist: fonttools ==4.39.0
Requires-Dist: importlib-resources ==5.12.0
Requires-Dist: kiwisolver ==1.4.4
Requires-Dist: matplotlib ==3.7.1
Requires-Dist: numpy ==1.23.5
Requires-Dist: packaging ==23.0
Requires-Dist: pandas ==1.5.3
Requires-Dist: patsy ==0.5.3
Requires-Dist: pillow ==9.4.0
Requires-Dist: pipenv-setup ==2.0.0
Requires-Dist: pipfile ==0.0.2
Requires-Dist: pyparsing ==3.0.9
Requires-Dist: python-dateutil ==2.8.2
Requires-Dist: pytz ==2022.7.1
Requires-Dist: six ==1.16.0
Requires-Dist: statsmodels ==0.13.5
Requires-Dist: toml ==0.10.0
Requires-Dist: zipp ==3.15.0
Requires-Dist: attrs ==19.1.0 ; python_version >= "2.7" and python_version not in "3.0, 3.1, 3.2, 3.3"
Requires-Dist: click ==7.0 ; python_version >= "2.7" and python_version not in "3.0, 3.1, 3.2, 3.3"
Requires-Dist: scipy ==1.10.1 ; python_version >= "3.10" and python_version < "3.12" and platform_system != "Windows" or platform_machine != "x86"
Requires-Dist: black ==19.3b0 ; python_version >= "3.6"
